pie_sensor/__init__.py
pie_sensor/hw_widgets.py
pie_sensor-0.1.0.dist-info/LICENSE
pie_sensor-0.1.0.dist-info/WHEEL
pie_sensor-0.1.0.dist-info/METADATA
pie_sensor-0.1.0.dist-info/RECORD
